{
  "id": "cia-uap-005-german-scientist-s-article-on-flying-discs",
  "title": "CIA-UAP-005, German Scientist's Article on 'Flying Discs'",
  "category": "intel",
  "agency": "CIA",
  "type": "pdf",
  "date_event": "1950",
  "date_released": "2026-06-12",
  "source_url": "https://www.war.gov/medialink/ufo/061226/release_03/documents/CIA-UAP-005-GERMAN_SCIENTISTS_ ARTICLE_ON_FLYING_DISCS.pdf",
  "pending_verification": false,
  "local_path": "downloads/pdf/cia-uap-005-german-scientist-s-article-on-flying-discs.pdf",
  "size_bytes": 1107431,
  "sha256": "85e84eb491e2331aebecb0ea021eb64d67795dc4c25197ca293ddfcffc81dee9",
  "redacted": false,
  "summary": "This 1950 CIA Information Report from Chile discusses a German scientist's article theorizing that \"Flying Discs\" could be explained as a new type of aircraft based on aerodynamic principles developed in German research facilities during and after WWI, using rotating cylinders or gas-turbines to create lift through boundary layer manipulation, rather than conventional wings. A redacted version of this report has been available on CIA's public website.",
  "score": {
    "value": 58,
    "components": {
      "sensor_quality": "eyewitness_only",
      "witness_credibility": "federal_agent",
      "corroboration": "single_witness_instrument",
      "kinematic_anomaly": "no_kinematic_data",
      "mundane_explanation_available": "weak_mundane_candidate",
      "official_disposition": "open_after_review"
    },
    "detail": {
      "sensor_quality": {
        "choice": "eyewitness_only",
        "value": 30,
        "weight": 0.25,
        "contribution": 7.5
      },
      "witness_credibility": {
        "choice": "federal_agent",
        "value": 90,
        "weight": 0.2,
        "contribution": 18.0
      },
      "corroboration": {
        "choice": "single_witness_instrument",
        "value": 60,
        "weight": 0.2,
        "contribution": 12.0
      },
      "kinematic_anomaly": {
        "choice": "no_kinematic_data",
        "value": 30,
        "weight": 0.15,
        "contribution": 4.5
      },
      "mundane_explanation_available": {
        "choice": "weak_mundane_candidate",
        "value": 70,
        "weight": 0.1,
        "contribution": 7.0
      },
      "official_disposition": {
        "choice": "open_after_review",
        "value": 90,
        "weight": 0.1,
        "contribution": 9.0
      }
    },
    "rubric_version": "1.0"
  },
  "extracted": {
    "text_path": "extracted/pdf-text/cia-uap-005-german-scientist-s-article-on-flying-discs.txt",
    "transcript_path": null,
    "thumbnail_path": null
  },
  "geo": {
    "lat": null,
    "lng": null,
    "place": null
  },
  "thumbnail_url": "https://www.war.gov/medialink/ufo/061226/release_03/thumbnails/CIA-UAP-005-GERMAN_SCIENTISTS_ ARTICLE_ON_FLYING_DISCS.jpg",
  "csv_raw_title": "CIA-UAP-005, German Scientist's Article on 'Flying Discs'",
  "audience": {
    "tldr": "Federal record documenting a UAP encounter (1950).",
    "what_we_know": [
      "Document originates from CIA.",
      "Encounter dated 1950.",
      "Document references: page, report, date, discs, chile."
    ],
    "what_we_dont": [
      "Specific geographic coordinates are not disclosed.",
      "No kinematic data (speed, altitude, maneuver) is attached.",
      "No official conclusion has been issued classifying the object as conventional."
    ],
    "mundane_candidate": "A conventional explanation is technically possible but has not been demonstrated.",
    "score_sentence": "Anomalousness Index 58/100. Top drivers: witness credibility (federal_agent), corroboration (single_witness_instrument).",
    "keywords": [
      "page",
      "report",
      "date",
      "discs",
      "chile",
      "grading",
      "source",
      "oved"
    ]
  }
}